plutorcon/__init__.py
plutorcon/client.py
plutorcon/models/__init__.py
plutorcon/models/colors.py
plutorcon/models/commands.py
plutorcon/models/player.py
plutorcon/models/server.py
plutorcon-1.0.3.dist-info/licenses/LICENSE
plutorcon-1.0.3.dist-info/METADATA
plutorcon-1.0.3.dist-info/WHEEL
plutorcon-1.0.3.dist-info/top_level.txt
plutorcon-1.0.3.dist-info/RECORD
