Metadata-Version: 2.4
Name: plutorcon
Version: 1.0.3
Summary: Python RCON client for Plutonium
Home-page: https://github.com/reusteur73/plutorcon
Author: ReuS
Project-URL: Documentation, https://github.com/reusteur73/plutorcon#readme
Project-URL: Source Code, https://github.com/reusteur73/plutorcon
Project-URL: Bug Tracker, https://github.com/reusteur73/plutorcon/issues
License-File: LICENSE
Dynamic: author
Dynamic: description
Dynamic: description-content-type
Dynamic: home-page
Dynamic: license-file
Dynamic: project-url
Dynamic: summary
